word_vectors/__init__.py
word_vectors/convert.py
word_vectors/read.py
word_vectors/utils.py
word_vectors/write.py
word_vectors-4.0.2.dist-info/LICENSE.txt
word_vectors-4.0.2.dist-info/METADATA
word_vectors-4.0.2.dist-info/WHEEL
word_vectors-4.0.2.dist-info/entry_points.txt
word_vectors-4.0.2.dist-info/top_level.txt
word_vectors-4.0.2.dist-info/RECORD
