Metadata-Version: 2.1
Name: word-vectors
Version: 4.0.2
Summary: Word Vectors
Home-page: https://github.com/blester125/word-vectors
Author: blester125
Author-email: blester125@gmail.com
License: MIT
Download-URL: https://github.com/blester125/word-vectors/archive/4.0.2.tar.gz
Platform: UNKNOWN
Classifier: Environment :: Console
Classifier: Intended Audience :: Science/Research
Classifier: Natural Language :: English
Classifier: Intended Audience :: Developers
Classifier: Programming Language :: Python :: 3 :: Only
Classifier: Topic :: Scientific/Engineering
Classifier: License :: OSI Approved :: MIT License
Classifier: Development Status :: 3 - Alpha
Requires-Python: >=3.6
Requires-Dist: file-or-name (>=1.1.3)
Requires-Dist: numpy
Provides-Extra: test
Requires-Dist: pytest ; extra == 'test'
